smime_email/__init__.py
smime_email/__main__.py
smime_email-1.0.1.dist-info/LICENSE.md
smime_email-1.0.1.dist-info/METADATA
smime_email-1.0.1.dist-info/WHEEL
smime_email-1.0.1.dist-info/RECORD
