Metadata-Version: 2.1
Name: smime-email
Version: 1.0.1
Summary: A Python library to generate a signed email
License: MIT
Author: Siemens
Requires-Python: >=3.10,<4.0
Classifier: License :: OSI Approved :: MIT License
Classifier: Programming Language :: Python :: 3
Classifier: Programming Language :: Python :: 3.10
Classifier: Programming Language :: Python :: 3.11
Classifier: Programming Language :: Python :: 3.12
Requires-Dist: cryptography (>=43.0.1,<45.0.0)
